CSSL/__init__.py
CSSL/setup_tools.py
CSSL/callbacks/__init__.py
CSSL/callbacks/byol_updates.py
CSSL/callbacks/data_monitor.py
CSSL/callbacks/knn_online.py
CSSL/callbacks/printing.py
CSSL/callbacks/ssl_online.py
CSSL/callbacks/variational.py
CSSL/callbacks/verification/__init__.py
CSSL/callbacks/verification/base.py
CSSL/callbacks/verification/batch_gradient.py
CSSL/callbacks/vision/__init__.py
CSSL/callbacks/vision/confused_logit.py
CSSL/callbacks/vision/image_generation.py
CSSL/datamodules/__init__.py
CSSL/datamodules/async_dataloader.py
CSSL/datamodules/binary_mnist_datamodule.py
CSSL/datamodules/cifar10_datamodule.py
CSSL/datamodules/cityscapes_datamodule.py
CSSL/datamodules/experience_source.py
CSSL/datamodules/fashion_mnist_datamodule.py
CSSL/datamodules/imagenet_datamodule.py
CSSL/datamodules/kitti_datamodule.py
CSSL/datamodules/mnist_datamodule.py
CSSL/datamodules/sklearn_datamodule.py
CSSL/datamodules/ssl_imagenet_datamodule.py
CSSL/datamodules/stl10_datamodule.py
CSSL/datamodules/vision_datamodule.py
CSSL/datamodules/vocdetection_datamodule.py
CSSL/datasets/__init__.py
CSSL/datasets/base_dataset.py
CSSL/datasets/cifar10_dataset.py
CSSL/datasets/concat_dataset.py
CSSL/datasets/dummy_dataset.py
CSSL/datasets/imagenet_dataset.py
CSSL/datasets/kitti_dataset.py
CSSL/datasets/mnist_dataset.py
CSSL/datasets/ssl_amdim_datasets.py
CSSL/losses/__init__.py
CSSL/losses/object_detection.py
CSSL/losses/rl.py
CSSL/losses/self_supervised_learning.py
CSSL/metrics/__init__.py
CSSL/metrics/aggregation.py
CSSL/metrics/object_detection.py
CSSL/models/__init__.py
CSSL/models/mnist_module.py
CSSL/models/regression/__init__.py
CSSL/models/regression/linear_regression.py
CSSL/models/regression/logistic_regression.py
CSSL/models/self_supervised/__init__.py
CSSL/models/self_supervised/evaluator.py
CSSL/models/self_supervised/resnets.py
CSSL/models/self_supervised/ssl_finetuner.py
CSSL/models/self_supervised/amdim/__init__.py
CSSL/models/self_supervised/amdim/amdim_module.py
ConSSL-0.0.1.dist-info/LICENSE
ConSSL-0.0.1.dist-info/METADATA
ConSSL-0.0.1.dist-info/WHEEL
ConSSL-0.0.1.dist-info/top_level.txt
ConSSL-0.0.1.dist-info/RECORD
