Metadata-Version: 2.1
Name: ConSSL
Version: 0.0.1
Summary: SOTA self-supervised contrastive learning models including simclrv2, byol, swav, moco, simsiam etc.
Home-page: https://github.com/sally20921/SimSiam
Author: Seri Lee
Author-email: sally20921@snu.ac.kr
License: MIT
Keywords: self-supervised learning,contrastive learning,SimCLR,BYOL,SwAV,MoCo,PIRL,SimSiam
Platform: UNKNOWN
Classifier: Intended Audience :: Developers
Classifier: Topic :: Scientific/Engineering :: Artificial Intelligence
Classifier: License :: OSI Approved :: MIT License
Classifier: Programming Language :: Python :: 3.8
Requires-Dist: torch
